inject_in_loop/__init__.py
inject_in_loop/base.py
inject_in_loop/main.py
InjectInLoop-1.0.2.dist-info/METADATA
InjectInLoop-1.0.2.dist-info/WHEEL
InjectInLoop-1.0.2.dist-info/top_level.txt
InjectInLoop-1.0.2.dist-info/RECORD
