Metadata-Version: 2.1
Name: InjectInLoop
Version: 1.0.2
Summary: This module lets you inject a function call between every iteration without doing it manually. Created mainly for fun :)
Home-page: https://github.com/jonatan1609/InjectInLoop
Author: Jonathan
Author-email: pybots.il@gmail.com
License: UNKNOWN
Platform: UNKNOWN
Classifier: License :: OSI Approved :: The Unlicense (Unlicense)
Classifier: Programming Language :: Python :: 3
Classifier: Operating System :: OS Independent
Requires-Python: >=3
